{
  "metadata": {
    "account_id": "627000756526718",
    "account_name": "JerseyEra's ad account",
    "period": "3d",
    "date_range": "2025-10-31..2025-11-02",
    "generated_at": "2025-11-03T03:53:34.660371Z",
    "source": "insights(level=account, breakdowns=[age,gender])"
  },
  "segments": [
    {
      "age": "35-44",
      "gender": "male",
      "impressions": 22398,
      "clicks": 531,
      "spend": 1254.98,
      "purchases": 4,
      "purchase_value": 5333.0,
      "ctr": 2.37,
      "cpa": 313.74,
      "roas": 4.25
    },
    {
      "age": "25-34",
      "gender": "male",
      "impressions": 20937,
      "clicks": 367,
      "spend": 854.81,
      "purchases": 4,
      "purchase_value": 7101.0,
      "ctr": 1.75,
      "cpa": 213.7,
      "roas": 8.31
    },
    {
      "age": "45-54",
      "gender": "male",
      "impressions": 8280,
      "clicks": 216,
      "spend": 597.61,
      "purchases": 0,
      "purchase_value": 0.0,
      "ctr": 2.61,
      "cpa": 0,
      "roas": 0.0
    },
    {
      "age": "18-24",
      "gender": "male",
      "impressions": 7645,
      "clicks": 158,
      "spend": 288.4,
      "purchases": 1,
      "purchase_value": 1836.0,
      "ctr": 2.07,
      "cpa": 288.4,
      "roas": 6.37
    },
    {
      "age": "55-64",
      "gender": "male",
      "impressions": 1407,
      "clicks": 33,
      "spend": 161.23,
      "purchases": 0,
      "purchase_value": 0.0,
      "ctr": 2.35,
      "cpa": 0,
      "roas": 0.0
    },
    {
      "age": "25-34",
      "gender": "female",
      "impressions": 2537,
      "clicks": 39,
      "spend": 132.58,
      "purchases": 0,
      "purchase_value": 0.0,
      "ctr": 1.54,
      "cpa": 0,
      "roas": 0.0
    },
    {
      "age": "18-24",
      "gender": "female",
      "impressions": 1992,
      "clicks": 56,
      "spend": 123.76,
      "purchases": 0,
      "purchase_value": 0.0,
      "ctr": 2.81,
      "cpa": 0,
      "roas": 0.0
    },
    {
      "age": "35-44",
      "gender": "female",
      "impressions": 1466,
      "clicks": 24,
      "spend": 98.64,
      "purchases": 0,
      "purchase_value": 0.0,
      "ctr": 1.64,
      "cpa": 0,
      "roas": 0.0
    },
    {
      "age": "65+",
      "gender": "male",
      "impressions": 942,
      "clicks": 24,
      "spend": 88.43,
      "purchases": 0,
      "purchase_value": 0.0,
      "ctr": 2.55,
      "cpa": 0,
      "roas": 0.0
    },
    {
      "age": "45-54",
      "gender": "female",
      "impressions": 670,
      "clicks": 14,
      "spend": 49.44,
      "purchases": 0,
      "purchase_value": 0.0,
      "ctr": 2.09,
      "cpa": 0,
      "roas": 0.0
    },
    {
      "age": "45-54",
      "gender": "unknown",
      "impressions": 195,
      "clicks": 1,
      "spend": 23.38,
      "purchases": 0,
      "purchase_value": 0.0,
      "ctr": 0.51,
      "cpa": 0,
      "roas": 0.0
    },
    {
      "age": "25-34",
      "gender": "unknown",
      "impressions": 173,
      "clicks": 2,
      "spend": 16.13,
      "purchases": 0,
      "purchase_value": 0.0,
      "ctr": 1.16,
      "cpa": 0,
      "roas": 0.0
    },
    {
      "age": "35-44",
      "gender": "unknown",
      "impressions": 341,
      "clicks": 5,
      "spend": 15.39,
      "purchases": 0,
      "purchase_value": 0.0,
      "ctr": 1.47,
      "cpa": 0,
      "roas": 0.0
    },
    {
      "age": "55-64",
      "gender": "female",
      "impressions": 129,
      "clicks": 5,
      "spend": 13.78,
      "purchases": 0,
      "purchase_value": 0.0,
      "ctr": 3.88,
      "cpa": 0,
      "roas": 0.0
    },
    {
      "age": "65+",
      "gender": "female",
      "impressions": 62,
      "clicks": 1,
      "spend": 5.84,
      "purchases": 0,
      "purchase_value": 0.0,
      "ctr": 1.61,
      "cpa": 0,
      "roas": 0.0
    },
    {
      "age": "18-24",
      "gender": "unknown",
      "impressions": 84,
      "clicks": 0,
      "spend": 3.7,
      "purchases": 0,
      "purchase_value": 0.0,
      "ctr": 0.0,
      "cpa": 0,
      "roas": 0.0
    },
    {
      "age": "55-64",
      "gender": "unknown",
      "impressions": 29,
      "clicks": 1,
      "spend": 3.55,
      "purchases": 0,
      "purchase_value": 0.0,
      "ctr": 3.45,
      "cpa": 0,
      "roas": 0.0
    },
    {
      "age": "65+",
      "gender": "unknown",
      "impressions": 14,
      "clicks": 0,
      "spend": 0.47,
      "purchases": 0,
      "purchase_value": 0.0,
      "ctr": 0.0,
      "cpa": 0,
      "roas": 0.0
    },
    {
      "age": "Unknown",
      "gender": "unknown",
      "impressions": 0,
      "clicks": 0,
      "spend": 0.0,
      "purchases": 0,
      "purchase_value": 0.0,
      "ctr": 0,
      "cpa": 0,
      "roas": 0
    }
  ],
  "totals": {
    "impressions": 69301,
    "clicks": 1477,
    "spend": 3732.12,
    "purchases": 9,
    "purchase_value": 14270.0,
    "roas": 3.82
  }
}