{
  "metadata": {
    "account_id": "954628458749162",
    "account_name": "GB Nueva Cuenta",
    "period": "3d",
    "date_range": "2025-11-21..2025-11-23",
    "generated_at": "2025-11-24T03:57:52.071071Z",
    "source": "insights(level=account, breakdowns=[age,gender])"
  },
  "segments": [
    {
      "age": "25-34",
      "gender": "male",
      "impressions": 160036,
      "clicks": 3593,
      "spend": 5015.8,
      "purchases": 7,
      "purchase_value": 11636.0,
      "ctr": 2.25,
      "cpa": 716.54,
      "roas": 2.32
    },
    {
      "age": "35-44",
      "gender": "male",
      "impressions": 110051,
      "clicks": 3357,
      "spend": 4875.82,
      "purchases": 7,
      "purchase_value": 16834.0,
      "ctr": 3.05,
      "cpa": 696.55,
      "roas": 3.45
    },
    {
      "age": "45-54",
      "gender": "male",
      "impressions": 64824,
      "clicks": 2194,
      "spend": 3029.12,
      "purchases": 7,
      "purchase_value": 14434.0,
      "ctr": 3.38,
      "cpa": 432.73,
      "roas": 4.77
    },
    {
      "age": "55-64",
      "gender": "male",
      "impressions": 37353,
      "clicks": 1258,
      "spend": 1600.72,
      "purchases": 3,
      "purchase_value": 4583.0,
      "ctr": 3.37,
      "cpa": 533.57,
      "roas": 2.86
    },
    {
      "age": "18-24",
      "gender": "male",
      "impressions": 34914,
      "clicks": 737,
      "spend": 870.3,
      "purchases": 2,
      "purchase_value": 3496.0,
      "ctr": 2.11,
      "cpa": 435.15,
      "roas": 4.02
    },
    {
      "age": "65+",
      "gender": "male",
      "impressions": 14890,
      "clicks": 507,
      "spend": 644.99,
      "purchases": 1,
      "purchase_value": 2448.0,
      "ctr": 3.4,
      "cpa": 644.99,
      "roas": 3.8
    },
    {
      "age": "25-34",
      "gender": "female",
      "impressions": 29044,
      "clicks": 347,
      "spend": 621.42,
      "purchases": 2,
      "purchase_value": 4896.0,
      "ctr": 1.19,
      "cpa": 310.71,
      "roas": 7.88
    },
    {
      "age": "35-44",
      "gender": "female",
      "impressions": 20423,
      "clicks": 294,
      "spend": 411.64,
      "purchases": 2,
      "purchase_value": 4696.0,
      "ctr": 1.44,
      "cpa": 205.82,
      "roas": 11.41
    },
    {
      "age": "45-54",
      "gender": "female",
      "impressions": 17406,
      "clicks": 241,
      "spend": 310.83,
      "purchases": 0,
      "purchase_value": 0.0,
      "ctr": 1.38,
      "cpa": 0,
      "roas": 0.0
    },
    {
      "age": "55-64",
      "gender": "female",
      "impressions": 12734,
      "clicks": 160,
      "spend": 156.96,
      "purchases": 0,
      "purchase_value": 0.0,
      "ctr": 1.26,
      "cpa": 0,
      "roas": 0.0
    },
    {
      "age": "18-24",
      "gender": "female",
      "impressions": 11756,
      "clicks": 82,
      "spend": 141.36,
      "purchases": 0,
      "purchase_value": 0.0,
      "ctr": 0.7,
      "cpa": 0,
      "roas": 0.0
    },
    {
      "age": "35-44",
      "gender": "unknown",
      "impressions": 1277,
      "clicks": 37,
      "spend": 70.94,
      "purchases": 0,
      "purchase_value": 0.0,
      "ctr": 2.9,
      "cpa": 0,
      "roas": 0.0
    },
    {
      "age": "65+",
      "gender": "female",
      "impressions": 5016,
      "clicks": 85,
      "spend": 62.33,
      "purchases": 0,
      "purchase_value": 0.0,
      "ctr": 1.69,
      "cpa": 0,
      "roas": 0.0
    },
    {
      "age": "45-54",
      "gender": "unknown",
      "impressions": 925,
      "clicks": 27,
      "spend": 51.68,
      "purchases": 0,
      "purchase_value": 0.0,
      "ctr": 2.92,
      "cpa": 0,
      "roas": 0.0
    },
    {
      "age": "25-34",
      "gender": "unknown",
      "impressions": 1332,
      "clicks": 45,
      "spend": 48.78,
      "purchases": 0,
      "purchase_value": 0.0,
      "ctr": 3.38,
      "cpa": 0,
      "roas": 0.0
    },
    {
      "age": "55-64",
      "gender": "unknown",
      "impressions": 326,
      "clicks": 7,
      "spend": 12.72,
      "purchases": 0,
      "purchase_value": 0.0,
      "ctr": 2.15,
      "cpa": 0,
      "roas": 0.0
    },
    {
      "age": "18-24",
      "gender": "unknown",
      "impressions": 615,
      "clicks": 4,
      "spend": 12.5,
      "purchases": 0,
      "purchase_value": 0.0,
      "ctr": 0.65,
      "cpa": 0,
      "roas": 0.0
    },
    {
      "age": "65+",
      "gender": "unknown",
      "impressions": 137,
      "clicks": 2,
      "spend": 9.91,
      "purchases": 0,
      "purchase_value": 0.0,
      "ctr": 1.46,
      "cpa": 0,
      "roas": 0.0
    },
    {
      "age": "Unknown",
      "gender": "unknown",
      "impressions": 1,
      "clicks": 0,
      "spend": 0.05,
      "purchases": 0,
      "purchase_value": 0.0,
      "ctr": 0.0,
      "cpa": 0,
      "roas": 0.0
    },
    {
      "age": "Unknown",
      "gender": "male",
      "impressions": 1,
      "clicks": 0,
      "spend": 0.03,
      "purchases": 0,
      "purchase_value": 0.0,
      "ctr": 0.0,
      "cpa": 0,
      "roas": 0.0
    }
  ],
  "totals": {
    "impressions": 523061,
    "clicks": 12977,
    "spend": 17947.9,
    "purchases": 31,
    "purchase_value": 63023.0,
    "roas": 3.51
  }
}