{
  "metadata": {
    "account_id": "3656788454467002",
    "account_name": "Blue Banana Brand México",
    "period": "90d",
    "date_range": "2025-07-09..2025-10-06",
    "generated_at": "2025-10-07T15:24:36.537936Z",
    "source": "insights(level=account, breakdowns=[age,gender])"
  },
  "segments": [
    {
      "age": "35-44",
      "gender": "male",
      "impressions": 103820,
      "clicks": 3215,
      "spend": 13254.02,
      "purchases": 10,
      "purchase_value": 15534.75,
      "ctr": 3.1,
      "cpa": 1325.4,
      "roas": 1.17
    },
    {
      "age": "45-54",
      "gender": "male",
      "impressions": 66982,
      "clicks": 3552,
      "spend": 11727.55,
      "purchases": 9,
      "purchase_value": 14280.6,
      "ctr": 5.3,
      "cpa": 1303.06,
      "roas": 1.22
    },
    {
      "age": "25-34",
      "gender": "male",
      "impressions": 106645,
      "clicks": 3001,
      "spend": 8460.39,
      "purchases": 8,
      "purchase_value": 7460.78,
      "ctr": 2.81,
      "cpa": 1057.55,
      "roas": 0.88
    },
    {
      "age": "55-64",
      "gender": "male",
      "impressions": 37464,
      "clicks": 3730,
      "spend": 5575.38,
      "purchases": 4,
      "purchase_value": 8445.79,
      "ctr": 9.96,
      "cpa": 1393.85,
      "roas": 1.51
    },
    {
      "age": "18-24",
      "gender": "male",
      "impressions": 45685,
      "clicks": 1166,
      "spend": 2637.12,
      "purchases": 2,
      "purchase_value": 2148.35,
      "ctr": 2.55,
      "cpa": 1318.56,
      "roas": 0.81
    },
    {
      "age": "45-54",
      "gender": "female",
      "impressions": 13560,
      "clicks": 583,
      "spend": 2543.91,
      "purchases": 1,
      "purchase_value": 1300.45,
      "ctr": 4.3,
      "cpa": 2543.91,
      "roas": 0.51
    },
    {
      "age": "65+",
      "gender": "male",
      "impressions": 21162,
      "clicks": 2981,
      "spend": 2227.39,
      "purchases": 1,
      "purchase_value": 648.65,
      "ctr": 14.09,
      "cpa": 2227.39,
      "roas": 0.29
    },
    {
      "age": "35-44",
      "gender": "female",
      "impressions": 16506,
      "clicks": 484,
      "spend": 2206.56,
      "purchases": 0,
      "purchase_value": 0.0,
      "ctr": 2.93,
      "cpa": 0,
      "roas": 0.0
    },
    {
      "age": "55-64",
      "gender": "female",
      "impressions": 7139,
      "clicks": 405,
      "spend": 1496.5,
      "purchases": 0,
      "purchase_value": 0.0,
      "ctr": 5.67,
      "cpa": 0,
      "roas": 0.0
    },
    {
      "age": "25-34",
      "gender": "female",
      "impressions": 15601,
      "clicks": 454,
      "spend": 1484.77,
      "purchases": 0,
      "purchase_value": 0.0,
      "ctr": 2.91,
      "cpa": 0,
      "roas": 0.0
    },
    {
      "age": "65+",
      "gender": "female",
      "impressions": 4823,
      "clicks": 257,
      "spend": 585.85,
      "purchases": 1,
      "purchase_value": 1305.36,
      "ctr": 5.33,
      "cpa": 585.85,
      "roas": 2.23
    },
    {
      "age": "18-24",
      "gender": "female",
      "impressions": 6156,
      "clicks": 148,
      "spend": 317.69,
      "purchases": 0,
      "purchase_value": 0.0,
      "ctr": 2.4,
      "cpa": 0,
      "roas": 0.0
    },
    {
      "age": "45-54",
      "gender": "unknown",
      "impressions": 1710,
      "clicks": 50,
      "spend": 309.22,
      "purchases": 0,
      "purchase_value": 0.0,
      "ctr": 2.92,
      "cpa": 0,
      "roas": 0.0
    },
    {
      "age": "35-44",
      "gender": "unknown",
      "impressions": 2502,
      "clicks": 67,
      "spend": 236.85,
      "purchases": 0,
      "purchase_value": 0.0,
      "ctr": 2.68,
      "cpa": 0,
      "roas": 0.0
    },
    {
      "age": "65+",
      "gender": "unknown",
      "impressions": 357,
      "clicks": 22,
      "spend": 182.56,
      "purchases": 1,
      "purchase_value": 949.37,
      "ctr": 6.16,
      "cpa": 182.56,
      "roas": 5.2
    },
    {
      "age": "55-64",
      "gender": "unknown",
      "impressions": 774,
      "clicks": 39,
      "spend": 99.45,
      "purchases": 0,
      "purchase_value": 0.0,
      "ctr": 5.04,
      "cpa": 0,
      "roas": 0.0
    },
    {
      "age": "25-34",
      "gender": "unknown",
      "impressions": 834,
      "clicks": 26,
      "spend": 64.57,
      "purchases": 0,
      "purchase_value": 0.0,
      "ctr": 3.12,
      "cpa": 0,
      "roas": 0.0
    },
    {
      "age": "18-24",
      "gender": "unknown",
      "impressions": 558,
      "clicks": 14,
      "spend": 15.42,
      "purchases": 0,
      "purchase_value": 0.0,
      "ctr": 2.51,
      "cpa": 0,
      "roas": 0.0
    },
    {
      "age": "Unknown",
      "gender": "unknown",
      "impressions": 2,
      "clicks": 0,
      "spend": 0.27,
      "purchases": 0,
      "purchase_value": 0.0,
      "ctr": 0.0,
      "cpa": 0,
      "roas": 0.0
    }
  ],
  "totals": {
    "impressions": 452280,
    "clicks": 20194,
    "spend": 53425.47,
    "purchases": 37,
    "purchase_value": 52074.1,
    "roas": 0.97
  }
}