{
  "metadata": {
    "account_id": "834887760925832",
    "account_name": "SEPUA",
    "period": "90d",
    "date_range": "2025-08-02..2025-10-30",
    "generated_at": "2025-10-31T09:23:35.522333Z",
    "source": "insights(level=account, breakdowns=[age,gender])"
  },
  "segments": [
    {
      "age": "35-44",
      "gender": "female",
      "impressions": 76740,
      "clicks": 1032,
      "spend": 11745.65,
      "purchases": 18,
      "purchase_value": 35653.7,
      "ctr": 1.34,
      "cpa": 652.54,
      "roas": 3.04
    },
    {
      "age": "25-34",
      "gender": "female",
      "impressions": 73744,
      "clicks": 899,
      "spend": 8027.15,
      "purchases": 10,
      "purchase_value": 22098.83,
      "ctr": 1.22,
      "cpa": 802.72,
      "roas": 2.75
    },
    {
      "age": "45-54",
      "gender": "female",
      "impressions": 30937,
      "clicks": 724,
      "spend": 7836.71,
      "purchases": 17,
      "purchase_value": 46381.4,
      "ctr": 2.34,
      "cpa": 460.98,
      "roas": 5.92
    },
    {
      "age": "35-44",
      "gender": "male",
      "impressions": 44948,
      "clicks": 594,
      "spend": 6658.09,
      "purchases": 11,
      "purchase_value": 44605.2,
      "ctr": 1.32,
      "cpa": 605.28,
      "roas": 6.7
    },
    {
      "age": "25-34",
      "gender": "male",
      "impressions": 45921,
      "clicks": 559,
      "spend": 5615.98,
      "purchases": 5,
      "purchase_value": 16708.9,
      "ctr": 1.22,
      "cpa": 1123.2,
      "roas": 2.98
    },
    {
      "age": "45-54",
      "gender": "male",
      "impressions": 17613,
      "clicks": 350,
      "spend": 4481.36,
      "purchases": 0,
      "purchase_value": 0.0,
      "ctr": 1.99,
      "cpa": 0,
      "roas": 0.0
    },
    {
      "age": "55-64",
      "gender": "female",
      "impressions": 9626,
      "clicks": 314,
      "spend": 3685.34,
      "purchases": 0,
      "purchase_value": 0.0,
      "ctr": 3.26,
      "cpa": 0,
      "roas": 0.0
    },
    {
      "age": "55-64",
      "gender": "male",
      "impressions": 7676,
      "clicks": 154,
      "spend": 2093.46,
      "purchases": 2,
      "purchase_value": 2645.0,
      "ctr": 2.01,
      "cpa": 1046.73,
      "roas": 1.26
    },
    {
      "age": "65+",
      "gender": "female",
      "impressions": 3492,
      "clicks": 169,
      "spend": 1196.29,
      "purchases": 0,
      "purchase_value": 0.0,
      "ctr": 4.84,
      "cpa": 0,
      "roas": 0.0
    },
    {
      "age": "65+",
      "gender": "male",
      "impressions": 2010,
      "clicks": 55,
      "spend": 434.26,
      "purchases": 0,
      "purchase_value": 0.0,
      "ctr": 2.74,
      "cpa": 0,
      "roas": 0.0
    },
    {
      "age": "55-64",
      "gender": "unknown",
      "impressions": 913,
      "clicks": 16,
      "spend": 350.08,
      "purchases": 0,
      "purchase_value": 0.0,
      "ctr": 1.75,
      "cpa": 0,
      "roas": 0.0
    },
    {
      "age": "25-34",
      "gender": "unknown",
      "impressions": 2514,
      "clicks": 58,
      "spend": 341.09,
      "purchases": 4,
      "purchase_value": 4990.0,
      "ctr": 2.31,
      "cpa": 85.27,
      "roas": 14.63
    },
    {
      "age": "45-54",
      "gender": "unknown",
      "impressions": 1942,
      "clicks": 35,
      "spend": 305.93,
      "purchases": 1,
      "purchase_value": 1949.0,
      "ctr": 1.8,
      "cpa": 305.93,
      "roas": 6.37
    },
    {
      "age": "35-44",
      "gender": "unknown",
      "impressions": 2995,
      "clicks": 21,
      "spend": 255.79,
      "purchases": 0,
      "purchase_value": 0.0,
      "ctr": 0.7,
      "cpa": 0,
      "roas": 0.0
    },
    {
      "age": "65+",
      "gender": "unknown",
      "impressions": 246,
      "clicks": 12,
      "spend": 42.02,
      "purchases": 0,
      "purchase_value": 0.0,
      "ctr": 4.88,
      "cpa": 0,
      "roas": 0.0
    },
    {
      "age": "Unknown",
      "gender": "unknown",
      "impressions": 0,
      "clicks": 0,
      "spend": 0.0,
      "purchases": 1,
      "purchase_value": 2299.0,
      "ctr": 0,
      "cpa": 0.0,
      "roas": 0
    }
  ],
  "totals": {
    "impressions": 321317,
    "clicks": 4992,
    "spend": 53069.2,
    "purchases": 69,
    "purchase_value": 177331.03,
    "roas": 3.34
  }
}