{
  "metadata": {
    "account_id": "505650941803538",
    "account_name": "Naturale 2024",
    "period": "7d",
    "date_range": "2025-10-22..2025-10-28",
    "generated_at": "2025-10-29T21:22:16.170380Z",
    "source": "insights(level=account, breakdowns=[age,gender])"
  },
  "segments": [
    {
      "age": "25-34",
      "gender": "female",
      "impressions": 233852,
      "clicks": 5028,
      "spend": 6348.56,
      "purchases": 17,
      "purchase_value": 18898.4,
      "ctr": 2.15,
      "cpa": 373.44,
      "roas": 2.98
    },
    {
      "age": "35-44",
      "gender": "female",
      "impressions": 122209,
      "clicks": 2995,
      "spend": 5714.15,
      "purchases": 17,
      "purchase_value": 20738.9,
      "ctr": 2.45,
      "cpa": 336.13,
      "roas": 3.63
    },
    {
      "age": "45-54",
      "gender": "female",
      "impressions": 47015,
      "clicks": 1603,
      "spend": 3191.72,
      "purchases": 6,
      "purchase_value": 6334.5,
      "ctr": 3.41,
      "cpa": 531.95,
      "roas": 1.98
    },
    {
      "age": "35-44",
      "gender": "male",
      "impressions": 51105,
      "clicks": 1125,
      "spend": 2170.84,
      "purchases": 1,
      "purchase_value": 899.1,
      "ctr": 2.2,
      "cpa": 2170.84,
      "roas": 0.41
    },
    {
      "age": "25-34",
      "gender": "male",
      "impressions": 74955,
      "clicks": 1676,
      "spend": 1830.55,
      "purchases": 1,
      "purchase_value": 1472.4,
      "ctr": 2.24,
      "cpa": 1830.55,
      "roas": 0.8
    },
    {
      "age": "55-64",
      "gender": "female",
      "impressions": 14018,
      "clicks": 705,
      "spend": 902.84,
      "purchases": 4,
      "purchase_value": 3076.5,
      "ctr": 5.03,
      "cpa": 225.71,
      "roas": 3.41
    },
    {
      "age": "45-54",
      "gender": "male",
      "impressions": 16980,
      "clicks": 450,
      "spend": 793.47,
      "purchases": 3,
      "purchase_value": 3447.9,
      "ctr": 2.65,
      "cpa": 264.49,
      "roas": 4.35
    },
    {
      "age": "18-24",
      "gender": "female",
      "impressions": 39303,
      "clicks": 1246,
      "spend": 651.37,
      "purchases": 0,
      "purchase_value": 0.0,
      "ctr": 3.17,
      "cpa": 0,
      "roas": 0.0
    },
    {
      "age": "65+",
      "gender": "female",
      "impressions": 5981,
      "clicks": 284,
      "spend": 491.61,
      "purchases": 2,
      "purchase_value": 2298.6,
      "ctr": 4.75,
      "cpa": 245.81,
      "roas": 4.68
    },
    {
      "age": "55-64",
      "gender": "male",
      "impressions": 5494,
      "clicks": 203,
      "spend": 285.44,
      "purchases": 0,
      "purchase_value": 0.0,
      "ctr": 3.69,
      "cpa": 0,
      "roas": 0.0
    },
    {
      "age": "18-24",
      "gender": "male",
      "impressions": 9712,
      "clicks": 332,
      "spend": 171.25,
      "purchases": 2,
      "purchase_value": 2048.4,
      "ctr": 3.42,
      "cpa": 85.63,
      "roas": 11.96
    },
    {
      "age": "35-44",
      "gender": "unknown",
      "impressions": 2757,
      "clicks": 82,
      "spend": 138.97,
      "purchases": 0,
      "purchase_value": 0.0,
      "ctr": 2.97,
      "cpa": 0,
      "roas": 0.0
    },
    {
      "age": "65+",
      "gender": "male",
      "impressions": 2605,
      "clicks": 110,
      "spend": 115.15,
      "purchases": 0,
      "purchase_value": 0.0,
      "ctr": 4.22,
      "cpa": 0,
      "roas": 0.0
    },
    {
      "age": "45-54",
      "gender": "unknown",
      "impressions": 1432,
      "clicks": 36,
      "spend": 101.01,
      "purchases": 0,
      "purchase_value": 0.0,
      "ctr": 2.51,
      "cpa": 0,
      "roas": 0.0
    },
    {
      "age": "25-34",
      "gender": "unknown",
      "impressions": 1712,
      "clicks": 39,
      "spend": 54.66,
      "purchases": 0,
      "purchase_value": 0.0,
      "ctr": 2.28,
      "cpa": 0,
      "roas": 0.0
    },
    {
      "age": "55-64",
      "gender": "unknown",
      "impressions": 252,
      "clicks": 8,
      "spend": 15.02,
      "purchases": 0,
      "purchase_value": 0.0,
      "ctr": 3.17,
      "cpa": 0,
      "roas": 0.0
    },
    {
      "age": "65+",
      "gender": "unknown",
      "impressions": 139,
      "clicks": 9,
      "spend": 9.46,
      "purchases": 0,
      "purchase_value": 0.0,
      "ctr": 6.47,
      "cpa": 0,
      "roas": 0.0
    },
    {
      "age": "18-24",
      "gender": "unknown",
      "impressions": 377,
      "clicks": 17,
      "spend": 6.0,
      "purchases": 0,
      "purchase_value": 0.0,
      "ctr": 4.51,
      "cpa": 0,
      "roas": 0.0
    },
    {
      "age": "Unknown",
      "gender": "unknown",
      "impressions": 0,
      "clicks": 0,
      "spend": 0.0,
      "purchases": 0,
      "purchase_value": 0.0,
      "ctr": 0,
      "cpa": 0,
      "roas": 0
    }
  ],
  "totals": {
    "impressions": 629898,
    "clicks": 15948,
    "spend": 22992.07,
    "purchases": 53,
    "purchase_value": 59214.7,
    "roas": 2.58
  }
}