{
  "metadata": {
    "account_id": "10157817450730790",
    "account_name": "Publicidad Ahal BUENA",
    "period": "90d",
    "date_range": "2025-07-10..2025-10-07",
    "generated_at": "2025-10-08T03:30:37.356791Z",
    "source": "insights(level=account, breakdowns=[age,gender])"
  },
  "segments": [
    {
      "age": "35-44",
      "gender": "female",
      "impressions": 518164,
      "clicks": 11559,
      "spend": 78470.95,
      "purchases": 119,
      "purchase_value": 248292.8,
      "ctr": 2.23,
      "cpa": 659.42,
      "roas": 3.16
    },
    {
      "age": "45-54",
      "gender": "female",
      "impressions": 297972,
      "clicks": 11093,
      "spend": 51888.34,
      "purchases": 76,
      "purchase_value": 136702.0,
      "ctr": 3.72,
      "cpa": 682.74,
      "roas": 2.63
    },
    {
      "age": "25-34",
      "gender": "female",
      "impressions": 426476,
      "clicks": 11679,
      "spend": 28829.1,
      "purchases": 35,
      "purchase_value": 73378.2,
      "ctr": 2.74,
      "cpa": 823.69,
      "roas": 2.55
    },
    {
      "age": "55-64",
      "gender": "female",
      "impressions": 179091,
      "clicks": 10569,
      "spend": 27937.43,
      "purchases": 29,
      "purchase_value": 44010.0,
      "ctr": 5.9,
      "cpa": 963.36,
      "roas": 1.58
    },
    {
      "age": "65+",
      "gender": "female",
      "impressions": 105038,
      "clicks": 7457,
      "spend": 13452.0,
      "purchases": 11,
      "purchase_value": 13917.0,
      "ctr": 7.1,
      "cpa": 1222.91,
      "roas": 1.03
    },
    {
      "age": "18-24",
      "gender": "female",
      "impressions": 225869,
      "clicks": 7198,
      "spend": 5452.0,
      "purchases": 2,
      "purchase_value": 3478.0,
      "ctr": 3.19,
      "cpa": 2726.0,
      "roas": 0.64
    },
    {
      "age": "55-64",
      "gender": "male",
      "impressions": 120140,
      "clicks": 6683,
      "spend": 3093.39,
      "purchases": 0,
      "purchase_value": 0.0,
      "ctr": 5.56,
      "cpa": 0,
      "roas": 0.0
    },
    {
      "age": "45-54",
      "gender": "male",
      "impressions": 116040,
      "clicks": 5849,
      "spend": 2969.41,
      "purchases": 2,
      "purchase_value": 2021.2,
      "ctr": 5.04,
      "cpa": 1484.7,
      "roas": 0.68
    },
    {
      "age": "35-44",
      "gender": "male",
      "impressions": 76557,
      "clicks": 3460,
      "spend": 2372.43,
      "purchases": 3,
      "purchase_value": 4329.0,
      "ctr": 4.52,
      "cpa": 790.81,
      "roas": 1.82
    },
    {
      "age": "65+",
      "gender": "male",
      "impressions": 77565,
      "clicks": 4396,
      "spend": 2213.64,
      "purchases": 0,
      "purchase_value": 0.0,
      "ctr": 5.67,
      "cpa": 0,
      "roas": 0.0
    },
    {
      "age": "45-54",
      "gender": "unknown",
      "impressions": 6639,
      "clicks": 134,
      "spend": 1810.25,
      "purchases": 0,
      "purchase_value": 0.0,
      "ctr": 2.02,
      "cpa": 0,
      "roas": 0.0
    },
    {
      "age": "25-34",
      "gender": "male",
      "impressions": 55622,
      "clicks": 2745,
      "spend": 1778.77,
      "purchases": 1,
      "purchase_value": 1837.0,
      "ctr": 4.94,
      "cpa": 1778.77,
      "roas": 1.03
    },
    {
      "age": "35-44",
      "gender": "unknown",
      "impressions": 9114,
      "clicks": 199,
      "spend": 1396.75,
      "purchases": 1,
      "purchase_value": 743.0,
      "ctr": 2.18,
      "cpa": 1396.75,
      "roas": 0.53
    },
    {
      "age": "55-64",
      "gender": "unknown",
      "impressions": 2123,
      "clicks": 86,
      "spend": 1006.84,
      "purchases": 3,
      "purchase_value": 5860.0,
      "ctr": 4.05,
      "cpa": 335.61,
      "roas": 5.82
    },
    {
      "age": "18-24",
      "gender": "male",
      "impressions": 26556,
      "clicks": 1295,
      "spend": 649.18,
      "purchases": 0,
      "purchase_value": 0.0,
      "ctr": 4.88,
      "cpa": 0,
      "roas": 0.0
    },
    {
      "age": "25-34",
      "gender": "unknown",
      "impressions": 4668,
      "clicks": 154,
      "spend": 521.1,
      "purchases": 0,
      "purchase_value": 0.0,
      "ctr": 3.3,
      "cpa": 0,
      "roas": 0.0
    },
    {
      "age": "65+",
      "gender": "unknown",
      "impressions": 1553,
      "clicks": 51,
      "spend": 317.88,
      "purchases": 0,
      "purchase_value": 0.0,
      "ctr": 3.28,
      "cpa": 0,
      "roas": 0.0
    },
    {
      "age": "18-24",
      "gender": "unknown",
      "impressions": 4779,
      "clicks": 142,
      "spend": 237.56,
      "purchases": 0,
      "purchase_value": 0.0,
      "ctr": 2.97,
      "cpa": 0,
      "roas": 0.0
    },
    {
      "age": "Unknown",
      "gender": "unknown",
      "impressions": 0,
      "clicks": 0,
      "spend": 0.0,
      "purchases": 0,
      "purchase_value": 0.0,
      "ctr": 0,
      "cpa": 0,
      "roas": 0
    }
  ],
  "totals": {
    "impressions": 2253966,
    "clicks": 84749,
    "spend": 224397.02,
    "purchases": 282,
    "purchase_value": 534568.2,
    "roas": 2.38
  }
}