{
  "metadata": {
    "account_id": "1733006760567787",
    "account_name": "Moscca Fine Fragrance",
    "period": "90d",
    "date_range": "2025-07-08..2025-10-05",
    "generated_at": "2025-10-06T03:37:52.211521Z",
    "source": "insights(level=account, breakdowns=[age,gender])"
  },
  "segments": [
    {
      "age": "25-34",
      "gender": "female",
      "impressions": 263467,
      "clicks": 3859,
      "spend": 17533.81,
      "purchases": 25,
      "purchase_value": 42581.55,
      "ctr": 1.46,
      "cpa": 701.35,
      "roas": 2.43
    },
    {
      "age": "35-44",
      "gender": "female",
      "impressions": 133921,
      "clicks": 2901,
      "spend": 15648.33,
      "purchases": 15,
      "purchase_value": 24712.3,
      "ctr": 2.17,
      "cpa": 1043.22,
      "roas": 1.58
    },
    {
      "age": "45-54",
      "gender": "male",
      "impressions": 72887,
      "clicks": 2354,
      "spend": 9641.83,
      "purchases": 19,
      "purchase_value": 27643.7,
      "ctr": 3.23,
      "cpa": 507.46,
      "roas": 2.87
    },
    {
      "age": "35-44",
      "gender": "male",
      "impressions": 96182,
      "clicks": 2215,
      "spend": 8461.73,
      "purchases": 10,
      "purchase_value": 12553.7,
      "ctr": 2.3,
      "cpa": 846.17,
      "roas": 1.48
    },
    {
      "age": "45-54",
      "gender": "female",
      "impressions": 53175,
      "clicks": 1651,
      "spend": 8402.61,
      "purchases": 8,
      "purchase_value": 11609.5,
      "ctr": 3.1,
      "cpa": 1050.33,
      "roas": 1.38
    },
    {
      "age": "25-34",
      "gender": "male",
      "impressions": 125990,
      "clicks": 2585,
      "spend": 8320.63,
      "purchases": 5,
      "purchase_value": 8721.5,
      "ctr": 2.05,
      "cpa": 1664.13,
      "roas": 1.05
    },
    {
      "age": "55-64",
      "gender": "male",
      "impressions": 42330,
      "clicks": 1676,
      "spend": 7640.13,
      "purchases": 10,
      "purchase_value": 10900.4,
      "ctr": 3.96,
      "cpa": 764.01,
      "roas": 1.43
    },
    {
      "age": "55-64",
      "gender": "female",
      "impressions": 22401,
      "clicks": 952,
      "spend": 5320.53,
      "purchases": 4,
      "purchase_value": 7382.2,
      "ctr": 4.25,
      "cpa": 1330.13,
      "roas": 1.39
    },
    {
      "age": "65+",
      "gender": "male",
      "impressions": 20100,
      "clicks": 874,
      "spend": 4278.47,
      "purchases": 2,
      "purchase_value": 2066.2,
      "ctr": 4.35,
      "cpa": 2139.24,
      "roas": 0.48
    },
    {
      "age": "18-24",
      "gender": "female",
      "impressions": 37326,
      "clicks": 598,
      "spend": 1826.34,
      "purchases": 3,
      "purchase_value": 3774.4,
      "ctr": 1.6,
      "cpa": 608.78,
      "roas": 2.07
    },
    {
      "age": "65+",
      "gender": "female",
      "impressions": 9525,
      "clicks": 392,
      "spend": 1568.46,
      "purchases": 1,
      "purchase_value": 1033.1,
      "ctr": 4.12,
      "cpa": 1568.46,
      "roas": 0.66
    },
    {
      "age": "18-24",
      "gender": "male",
      "impressions": 21052,
      "clicks": 394,
      "spend": 1535.22,
      "purchases": 3,
      "purchase_value": 3289.1,
      "ctr": 1.87,
      "cpa": 511.74,
      "roas": 2.14
    },
    {
      "age": "35-44",
      "gender": "unknown",
      "impressions": 3636,
      "clicks": 83,
      "spend": 256.31,
      "purchases": 0,
      "purchase_value": 0.0,
      "ctr": 2.28,
      "cpa": 0,
      "roas": 0.0
    },
    {
      "age": "55-64",
      "gender": "unknown",
      "impressions": 954,
      "clicks": 16,
      "spend": 200.89,
      "purchases": 0,
      "purchase_value": 0.0,
      "ctr": 1.68,
      "cpa": 0,
      "roas": 0.0
    },
    {
      "age": "25-34",
      "gender": "unknown",
      "impressions": 3959,
      "clicks": 54,
      "spend": 193.25,
      "purchases": 0,
      "purchase_value": 0.0,
      "ctr": 1.36,
      "cpa": 0,
      "roas": 0.0
    },
    {
      "age": "45-54",
      "gender": "unknown",
      "impressions": 1847,
      "clicks": 46,
      "spend": 172.42,
      "purchases": 0,
      "purchase_value": 0.0,
      "ctr": 2.49,
      "cpa": 0,
      "roas": 0.0
    },
    {
      "age": "18-24",
      "gender": "unknown",
      "impressions": 1202,
      "clicks": 20,
      "spend": 54.6,
      "purchases": 0,
      "purchase_value": 0.0,
      "ctr": 1.66,
      "cpa": 0,
      "roas": 0.0
    },
    {
      "age": "65+",
      "gender": "unknown",
      "impressions": 228,
      "clicks": 6,
      "spend": 37.77,
      "purchases": 0,
      "purchase_value": 0.0,
      "ctr": 2.63,
      "cpa": 0,
      "roas": 0.0
    },
    {
      "age": "Unknown",
      "gender": "unknown",
      "impressions": 0,
      "clicks": 0,
      "spend": 0.0,
      "purchases": 0,
      "purchase_value": 0.0,
      "ctr": 0,
      "cpa": 0,
      "roas": 0
    }
  ],
  "totals": {
    "impressions": 910182,
    "clicks": 20676,
    "spend": 91093.33,
    "purchases": 105,
    "purchase_value": 156267.65,
    "roas": 1.72
  }
}