{
  "metadata": {
    "account_id": "1530776461009181",
    "account_name": "YEKE ADS",
    "period": "3d",
    "date_range": "2025-09-29..2025-10-01",
    "generated_at": "2025-10-02T09:21:58.839211Z",
    "source": "insights(level=account, breakdowns=[age,gender])"
  },
  "segments": [
    {
      "age": "35-44",
      "gender": "male",
      "impressions": 5899,
      "clicks": 318,
      "spend": 404.9,
      "purchases": 2,
      "purchase_value": 2682.0,
      "ctr": 5.39,
      "cpa": 202.45,
      "roas": 6.62
    },
    {
      "age": "45-54",
      "gender": "male",
      "impressions": 7495,
      "clicks": 711,
      "spend": 327.68,
      "purchases": 2,
      "purchase_value": 4652.0,
      "ctr": 9.49,
      "cpa": 163.84,
      "roas": 14.2
    },
    {
      "age": "35-44",
      "gender": "female",
      "impressions": 2820,
      "clicks": 114,
      "spend": 265.38,
      "purchases": 0,
      "purchase_value": 0.0,
      "ctr": 4.04,
      "cpa": 0,
      "roas": 0.0
    },
    {
      "age": "25-34",
      "gender": "male",
      "impressions": 6595,
      "clicks": 298,
      "spend": 264.12,
      "purchases": 0,
      "purchase_value": 0.0,
      "ctr": 4.52,
      "cpa": 0,
      "roas": 0.0
    },
    {
      "age": "55-64",
      "gender": "male",
      "impressions": 8672,
      "clicks": 936,
      "spend": 263.42,
      "purchases": 0,
      "purchase_value": 0.0,
      "ctr": 10.79,
      "cpa": 0,
      "roas": 0.0
    },
    {
      "age": "45-54",
      "gender": "female",
      "impressions": 2528,
      "clicks": 155,
      "spend": 217.87,
      "purchases": 0,
      "purchase_value": 0.0,
      "ctr": 6.13,
      "cpa": 0,
      "roas": 0.0
    },
    {
      "age": "55-64",
      "gender": "female",
      "impressions": 2079,
      "clicks": 193,
      "spend": 200.33,
      "purchases": 1,
      "purchase_value": 1125.0,
      "ctr": 9.28,
      "cpa": 200.33,
      "roas": 5.62
    },
    {
      "age": "65+",
      "gender": "male",
      "impressions": 5410,
      "clicks": 678,
      "spend": 181.83,
      "purchases": 0,
      "purchase_value": 0.0,
      "ctr": 12.53,
      "cpa": 0,
      "roas": 0.0
    },
    {
      "age": "25-34",
      "gender": "female",
      "impressions": 4142,
      "clicks": 155,
      "spend": 148.38,
      "purchases": 0,
      "purchase_value": 0.0,
      "ctr": 3.74,
      "cpa": 0,
      "roas": 0.0
    },
    {
      "age": "18-24",
      "gender": "female",
      "impressions": 5064,
      "clicks": 204,
      "spend": 107.26,
      "purchases": 0,
      "purchase_value": 0.0,
      "ctr": 4.03,
      "cpa": 0,
      "roas": 0.0
    },
    {
      "age": "18-24",
      "gender": "male",
      "impressions": 4150,
      "clicks": 157,
      "spend": 82.79,
      "purchases": 0,
      "purchase_value": 0.0,
      "ctr": 3.78,
      "cpa": 0,
      "roas": 0.0
    },
    {
      "age": "65+",
      "gender": "female",
      "impressions": 1169,
      "clicks": 113,
      "spend": 49.87,
      "purchases": 0,
      "purchase_value": 0.0,
      "ctr": 9.67,
      "cpa": 0,
      "roas": 0.0
    },
    {
      "age": "55-64",
      "gender": "unknown",
      "impressions": 64,
      "clicks": 4,
      "spend": 38.34,
      "purchases": 0,
      "purchase_value": 0.0,
      "ctr": 6.25,
      "cpa": 0,
      "roas": 0.0
    },
    {
      "age": "45-54",
      "gender": "unknown",
      "impressions": 100,
      "clicks": 5,
      "spend": 6.6,
      "purchases": 0,
      "purchase_value": 0.0,
      "ctr": 5.0,
      "cpa": 0,
      "roas": 0.0
    },
    {
      "age": "35-44",
      "gender": "unknown",
      "impressions": 116,
      "clicks": 1,
      "spend": 3.76,
      "purchases": 0,
      "purchase_value": 0.0,
      "ctr": 0.86,
      "cpa": 0,
      "roas": 0.0
    },
    {
      "age": "18-24",
      "gender": "unknown",
      "impressions": 120,
      "clicks": 2,
      "spend": 2.17,
      "purchases": 0,
      "purchase_value": 0.0,
      "ctr": 1.67,
      "cpa": 0,
      "roas": 0.0
    },
    {
      "age": "25-34",
      "gender": "unknown",
      "impressions": 71,
      "clicks": 2,
      "spend": 1.39,
      "purchases": 0,
      "purchase_value": 0.0,
      "ctr": 2.82,
      "cpa": 0,
      "roas": 0.0
    },
    {
      "age": "65+",
      "gender": "unknown",
      "impressions": 27,
      "clicks": 0,
      "spend": 0.74,
      "purchases": 0,
      "purchase_value": 0.0,
      "ctr": 0.0,
      "cpa": 0,
      "roas": 0.0
    },
    {
      "age": "Unknown",
      "gender": "unknown",
      "impressions": 0,
      "clicks": 0,
      "spend": 0.0,
      "purchases": 0,
      "purchase_value": 0.0,
      "ctr": 0,
      "cpa": 0,
      "roas": 0
    }
  ],
  "totals": {
    "impressions": 56521,
    "clicks": 4046,
    "spend": 2566.83,
    "purchases": 5,
    "purchase_value": 8459.0,
    "roas": 3.3
  }
}