{
  "metadata": {
    "account_id": "1530776461009181",
    "account_name": "YEKE ADS",
    "period": "7d",
    "date_range": "2025-09-30..2025-10-06",
    "generated_at": "2025-10-07T21:19:24.833822Z",
    "source": "insights(level=account, breakdowns=[age,gender])"
  },
  "segments": [
    {
      "age": "35-44",
      "gender": "male",
      "impressions": 13768,
      "clicks": 778,
      "spend": 940.93,
      "purchases": 3,
      "purchase_value": 3637.0,
      "ctr": 5.65,
      "cpa": 313.64,
      "roas": 3.87
    },
    {
      "age": "45-54",
      "gender": "male",
      "impressions": 18513,
      "clicks": 1541,
      "spend": 707.3,
      "purchases": 2,
      "purchase_value": 4652.0,
      "ctr": 8.32,
      "cpa": 353.65,
      "roas": 6.58
    },
    {
      "age": "35-44",
      "gender": "female",
      "impressions": 6778,
      "clicks": 221,
      "spend": 655.55,
      "purchases": 1,
      "purchase_value": 1870.0,
      "ctr": 3.26,
      "cpa": 655.55,
      "roas": 2.85
    },
    {
      "age": "25-34",
      "gender": "male",
      "impressions": 17146,
      "clicks": 644,
      "spend": 602.4,
      "purchases": 0,
      "purchase_value": 0.0,
      "ctr": 3.76,
      "cpa": 0,
      "roas": 0.0
    },
    {
      "age": "55-64",
      "gender": "male",
      "impressions": 21342,
      "clicks": 2146,
      "spend": 586.66,
      "purchases": 0,
      "purchase_value": 0.0,
      "ctr": 10.06,
      "cpa": 0,
      "roas": 0.0
    },
    {
      "age": "45-54",
      "gender": "female",
      "impressions": 5585,
      "clicks": 324,
      "spend": 518.62,
      "purchases": 0,
      "purchase_value": 0.0,
      "ctr": 5.8,
      "cpa": 0,
      "roas": 0.0
    },
    {
      "age": "65+",
      "gender": "male",
      "impressions": 14820,
      "clicks": 1765,
      "spend": 474.53,
      "purchases": 0,
      "purchase_value": 0.0,
      "ctr": 11.91,
      "cpa": 0,
      "roas": 0.0
    },
    {
      "age": "55-64",
      "gender": "female",
      "impressions": 4462,
      "clicks": 377,
      "spend": 419.97,
      "purchases": 1,
      "purchase_value": 1125.0,
      "ctr": 8.45,
      "cpa": 419.97,
      "roas": 2.68
    },
    {
      "age": "25-34",
      "gender": "female",
      "impressions": 10062,
      "clicks": 386,
      "spend": 338.91,
      "purchases": 0,
      "purchase_value": 0.0,
      "ctr": 3.84,
      "cpa": 0,
      "roas": 0.0
    },
    {
      "age": "18-24",
      "gender": "female",
      "impressions": 14196,
      "clicks": 452,
      "spend": 278.71,
      "purchases": 0,
      "purchase_value": 0.0,
      "ctr": 3.18,
      "cpa": 0,
      "roas": 0.0
    },
    {
      "age": "18-24",
      "gender": "male",
      "impressions": 12619,
      "clicks": 362,
      "spend": 225.41,
      "purchases": 0,
      "purchase_value": 0.0,
      "ctr": 2.87,
      "cpa": 0,
      "roas": 0.0
    },
    {
      "age": "65+",
      "gender": "female",
      "impressions": 2685,
      "clicks": 258,
      "spend": 127.09,
      "purchases": 0,
      "purchase_value": 0.0,
      "ctr": 9.61,
      "cpa": 0,
      "roas": 0.0
    },
    {
      "age": "55-64",
      "gender": "unknown",
      "impressions": 153,
      "clicks": 9,
      "spend": 41.73,
      "purchases": 0,
      "purchase_value": 0.0,
      "ctr": 5.88,
      "cpa": 0,
      "roas": 0.0
    },
    {
      "age": "45-54",
      "gender": "unknown",
      "impressions": 240,
      "clicks": 11,
      "spend": 21.58,
      "purchases": 0,
      "purchase_value": 0.0,
      "ctr": 4.58,
      "cpa": 0,
      "roas": 0.0
    },
    {
      "age": "35-44",
      "gender": "unknown",
      "impressions": 247,
      "clicks": 3,
      "spend": 10.47,
      "purchases": 0,
      "purchase_value": 0.0,
      "ctr": 1.21,
      "cpa": 0,
      "roas": 0.0
    },
    {
      "age": "18-24",
      "gender": "unknown",
      "impressions": 331,
      "clicks": 7,
      "spend": 5.91,
      "purchases": 0,
      "purchase_value": 0.0,
      "ctr": 2.11,
      "cpa": 0,
      "roas": 0.0
    },
    {
      "age": "25-34",
      "gender": "unknown",
      "impressions": 200,
      "clicks": 8,
      "spend": 4.34,
      "purchases": 0,
      "purchase_value": 0.0,
      "ctr": 4.0,
      "cpa": 0,
      "roas": 0.0
    },
    {
      "age": "65+",
      "gender": "unknown",
      "impressions": 59,
      "clicks": 3,
      "spend": 1.36,
      "purchases": 0,
      "purchase_value": 0.0,
      "ctr": 5.08,
      "cpa": 0,
      "roas": 0.0
    },
    {
      "age": "Unknown",
      "gender": "unknown",
      "impressions": 0,
      "clicks": 0,
      "spend": 0.0,
      "purchases": 1,
      "purchase_value": 1225.0,
      "ctr": 0,
      "cpa": 0.0,
      "roas": 0
    }
  ],
  "totals": {
    "impressions": 143206,
    "clicks": 9295,
    "spend": 5961.47,
    "purchases": 8,
    "purchase_value": 12509.0,
    "roas": 2.1
  }
}