{
  "metadata": {
    "account_id": "3189193134676120",
    "account_name": "Piu Pieza Unica",
    "period": "7d",
    "date_range": "2025-11-13..2025-11-19",
    "generated_at": "2025-11-20T21:20:46.995508Z",
    "source": "insights(level=account, breakdowns=[age,gender])"
  },
  "segments": [
    {
      "age": "35-44",
      "gender": "female",
      "impressions": 30110,
      "clicks": 457,
      "spend": 3772.09,
      "purchases": 10,
      "purchase_value": 7802.0,
      "ctr": 1.52,
      "cpa": 377.21,
      "roas": 2.07
    },
    {
      "age": "25-34",
      "gender": "female",
      "impressions": 36008,
      "clicks": 463,
      "spend": 2701.69,
      "purchases": 6,
      "purchase_value": 4746.0,
      "ctr": 1.29,
      "cpa": 450.28,
      "roas": 1.76
    },
    {
      "age": "45-54",
      "gender": "female",
      "impressions": 7803,
      "clicks": 226,
      "spend": 1580.32,
      "purchases": 4,
      "purchase_value": 4394.0,
      "ctr": 2.9,
      "cpa": 395.08,
      "roas": 2.78
    },
    {
      "age": "18-24",
      "gender": "female",
      "impressions": 7960,
      "clicks": 89,
      "spend": 466.62,
      "purchases": 0,
      "purchase_value": 0.0,
      "ctr": 1.12,
      "cpa": 0,
      "roas": 0.0
    },
    {
      "age": "55-64",
      "gender": "female",
      "impressions": 1557,
      "clicks": 75,
      "spend": 461.33,
      "purchases": 1,
      "purchase_value": 468.0,
      "ctr": 4.82,
      "cpa": 461.33,
      "roas": 1.01
    },
    {
      "age": "35-44",
      "gender": "male",
      "impressions": 4020,
      "clicks": 35,
      "spend": 294.74,
      "purchases": 0,
      "purchase_value": 0.0,
      "ctr": 0.87,
      "cpa": 0,
      "roas": 0.0
    },
    {
      "age": "25-34",
      "gender": "male",
      "impressions": 5298,
      "clicks": 35,
      "spend": 264.95,
      "purchases": 1,
      "purchase_value": 378.0,
      "ctr": 0.66,
      "cpa": 264.95,
      "roas": 1.43
    },
    {
      "age": "65+",
      "gender": "female",
      "impressions": 659,
      "clicks": 19,
      "spend": 200.27,
      "purchases": 0,
      "purchase_value": 0.0,
      "ctr": 2.88,
      "cpa": 0,
      "roas": 0.0
    },
    {
      "age": "45-54",
      "gender": "male",
      "impressions": 561,
      "clicks": 5,
      "spend": 50.21,
      "purchases": 0,
      "purchase_value": 0.0,
      "ctr": 0.89,
      "cpa": 0,
      "roas": 0.0
    },
    {
      "age": "35-44",
      "gender": "unknown",
      "impressions": 519,
      "clicks": 2,
      "spend": 47.47,
      "purchases": 0,
      "purchase_value": 0.0,
      "ctr": 0.39,
      "cpa": 0,
      "roas": 0.0
    },
    {
      "age": "18-24",
      "gender": "male",
      "impressions": 1105,
      "clicks": 10,
      "spend": 45.14,
      "purchases": 0,
      "purchase_value": 0.0,
      "ctr": 0.9,
      "cpa": 0,
      "roas": 0.0
    },
    {
      "age": "45-54",
      "gender": "unknown",
      "impressions": 240,
      "clicks": 4,
      "spend": 30.07,
      "purchases": 0,
      "purchase_value": 0.0,
      "ctr": 1.67,
      "cpa": 0,
      "roas": 0.0
    },
    {
      "age": "25-34",
      "gender": "unknown",
      "impressions": 211,
      "clicks": 4,
      "spend": 12.56,
      "purchases": 0,
      "purchase_value": 0.0,
      "ctr": 1.9,
      "cpa": 0,
      "roas": 0.0
    },
    {
      "age": "55-64",
      "gender": "male",
      "impressions": 108,
      "clicks": 0,
      "spend": 9.96,
      "purchases": 0,
      "purchase_value": 0.0,
      "ctr": 0.0,
      "cpa": 0,
      "roas": 0.0
    },
    {
      "age": "55-64",
      "gender": "unknown",
      "impressions": 33,
      "clicks": 1,
      "spend": 3.99,
      "purchases": 0,
      "purchase_value": 0.0,
      "ctr": 3.03,
      "cpa": 0,
      "roas": 0.0
    },
    {
      "age": "65+",
      "gender": "male",
      "impressions": 81,
      "clicks": 0,
      "spend": 3.27,
      "purchases": 0,
      "purchase_value": 0.0,
      "ctr": 0.0,
      "cpa": 0,
      "roas": 0.0
    },
    {
      "age": "18-24",
      "gender": "unknown",
      "impressions": 48,
      "clicks": 2,
      "spend": 3.12,
      "purchases": 0,
      "purchase_value": 0.0,
      "ctr": 4.17,
      "cpa": 0,
      "roas": 0.0
    },
    {
      "age": "Unknown",
      "gender": "female",
      "impressions": 1,
      "clicks": 0,
      "spend": 0.18,
      "purchases": 0,
      "purchase_value": 0.0,
      "ctr": 0.0,
      "cpa": 0,
      "roas": 0.0
    },
    {
      "age": "65+",
      "gender": "unknown",
      "impressions": 2,
      "clicks": 1,
      "spend": 0.11,
      "purchases": 0,
      "purchase_value": 0.0,
      "ctr": 50.0,
      "cpa": 0,
      "roas": 0.0
    },
    {
      "age": "Unknown",
      "gender": "unknown",
      "impressions": 0,
      "clicks": 0,
      "spend": 0.0,
      "purchases": 0,
      "purchase_value": 0.0,
      "ctr": 0,
      "cpa": 0,
      "roas": 0
    }
  ],
  "totals": {
    "impressions": 96324,
    "clicks": 1428,
    "spend": 9948.09,
    "purchases": 22,
    "purchase_value": 17788.0,
    "roas": 1.79
  }
}