{
  "metadata": {
    "account_id": "1220340971806734",
    "account_name": "Rose&Mimosas",
    "period": "3d",
    "date_range": "2025-11-16..2025-11-18",
    "generated_at": "2025-11-19T15:25:59.178464Z",
    "source": "insights(level=account, breakdowns=[age,gender])"
  },
  "segments": [
    {
      "age": "35-44",
      "gender": "female",
      "impressions": 52316,
      "clicks": 1164,
      "spend": 10196.33,
      "purchases": 15,
      "purchase_value": 51256.97,
      "ctr": 2.22,
      "cpa": 679.76,
      "roas": 5.03
    },
    {
      "age": "25-34",
      "gender": "female",
      "impressions": 68611,
      "clicks": 1130,
      "spend": 7983.26,
      "purchases": 12,
      "purchase_value": 35878.0,
      "ctr": 1.65,
      "cpa": 665.27,
      "roas": 4.49
    },
    {
      "age": "45-54",
      "gender": "female",
      "impressions": 14448,
      "clicks": 507,
      "spend": 3748.59,
      "purchases": 2,
      "purchase_value": 4526.43,
      "ctr": 3.51,
      "cpa": 1874.3,
      "roas": 1.21
    },
    {
      "age": "55-64",
      "gender": "female",
      "impressions": 4014,
      "clicks": 172,
      "spend": 1234.3,
      "purchases": 0,
      "purchase_value": 0.0,
      "ctr": 4.29,
      "cpa": 0,
      "roas": 0.0
    },
    {
      "age": "18-24",
      "gender": "female",
      "impressions": 9815,
      "clicks": 136,
      "spend": 651.09,
      "purchases": 0,
      "purchase_value": 0.0,
      "ctr": 1.39,
      "cpa": 0,
      "roas": 0.0
    },
    {
      "age": "65+",
      "gender": "female",
      "impressions": 1293,
      "clicks": 58,
      "spend": 355.03,
      "purchases": 1,
      "purchase_value": 3538.0,
      "ctr": 4.49,
      "cpa": 355.03,
      "roas": 9.97
    },
    {
      "age": "35-44",
      "gender": "unknown",
      "impressions": 1389,
      "clicks": 19,
      "spend": 220.82,
      "purchases": 2,
      "purchase_value": 2838.4,
      "ctr": 1.37,
      "cpa": 110.41,
      "roas": 12.85
    },
    {
      "age": "35-44",
      "gender": "male",
      "impressions": 2151,
      "clicks": 42,
      "spend": 196.71,
      "purchases": 0,
      "purchase_value": 0.0,
      "ctr": 1.95,
      "cpa": 0,
      "roas": 0.0
    },
    {
      "age": "25-34",
      "gender": "male",
      "impressions": 2646,
      "clicks": 24,
      "spend": 156.77,
      "purchases": 0,
      "purchase_value": 0.0,
      "ctr": 0.91,
      "cpa": 0,
      "roas": 0.0
    },
    {
      "age": "45-54",
      "gender": "unknown",
      "impressions": 584,
      "clicks": 13,
      "spend": 103.96,
      "purchases": 0,
      "purchase_value": 0.0,
      "ctr": 2.23,
      "cpa": 0,
      "roas": 0.0
    },
    {
      "age": "25-34",
      "gender": "unknown",
      "impressions": 619,
      "clicks": 14,
      "spend": 66.33,
      "purchases": 1,
      "purchase_value": 2698.4,
      "ctr": 2.26,
      "cpa": 66.33,
      "roas": 40.68
    },
    {
      "age": "45-54",
      "gender": "male",
      "impressions": 582,
      "clicks": 6,
      "spend": 63.24,
      "purchases": 0,
      "purchase_value": 0.0,
      "ctr": 1.03,
      "cpa": 0,
      "roas": 0.0
    },
    {
      "age": "55-64",
      "gender": "unknown",
      "impressions": 138,
      "clicks": 10,
      "spend": 23.05,
      "purchases": 0,
      "purchase_value": 0.0,
      "ctr": 7.25,
      "cpa": 0,
      "roas": 0.0
    },
    {
      "age": "55-64",
      "gender": "male",
      "impressions": 156,
      "clicks": 1,
      "spend": 16.72,
      "purchases": 0,
      "purchase_value": 0.0,
      "ctr": 0.64,
      "cpa": 0,
      "roas": 0.0
    },
    {
      "age": "18-24",
      "gender": "male",
      "impressions": 389,
      "clicks": 3,
      "spend": 14.85,
      "purchases": 0,
      "purchase_value": 0.0,
      "ctr": 0.77,
      "cpa": 0,
      "roas": 0.0
    },
    {
      "age": "65+",
      "gender": "male",
      "impressions": 78,
      "clicks": 2,
      "spend": 7.73,
      "purchases": 0,
      "purchase_value": 0.0,
      "ctr": 2.56,
      "cpa": 0,
      "roas": 0.0
    },
    {
      "age": "65+",
      "gender": "unknown",
      "impressions": 30,
      "clicks": 0,
      "spend": 5.93,
      "purchases": 0,
      "purchase_value": 0.0,
      "ctr": 0.0,
      "cpa": 0,
      "roas": 0.0
    },
    {
      "age": "18-24",
      "gender": "unknown",
      "impressions": 25,
      "clicks": 0,
      "spend": 0.44,
      "purchases": 0,
      "purchase_value": 0.0,
      "ctr": 0.0,
      "cpa": 0,
      "roas": 0.0
    },
    {
      "age": "Unknown",
      "gender": "female",
      "impressions": 2,
      "clicks": 0,
      "spend": 0.04,
      "purchases": 0,
      "purchase_value": 0.0,
      "ctr": 0.0,
      "cpa": 0,
      "roas": 0.0
    },
    {
      "age": "Unknown",
      "gender": "unknown",
      "impressions": 0,
      "clicks": 0,
      "spend": 0.0,
      "purchases": 0,
      "purchase_value": 0.0,
      "ctr": 0,
      "cpa": 0,
      "roas": 0
    }
  ],
  "totals": {
    "impressions": 159286,
    "clicks": 3301,
    "spend": 25045.19,
    "purchases": 33,
    "purchase_value": 100736.2,
    "roas": 4.02
  }
}