{
  "metadata": {
    "account_id": "1070900890358939",
    "account_name": "Dr. Mon Ecommerce",
    "period": "14d",
    "date_range": "2025-09-03..2025-09-16",
    "generated_at": "2025-09-17T03:29:32.975957Z",
    "source": "insights(level=account, breakdowns=[age,gender])"
  },
  "segments": [
    {
      "age": "45-54",
      "gender": "male",
      "impressions": 213221,
      "clicks": 3880,
      "spend": 21702.07,
      "purchases": 39,
      "purchase_value": 46588.45,
      "ctr": 1.82,
      "cpa": 556.46,
      "roas": 2.15
    },
    {
      "age": "55-64",
      "gender": "male",
      "impressions": 116431,
      "clicks": 2498,
      "spend": 14807.45,
      "purchases": 30,
      "purchase_value": 46364.05,
      "ctr": 2.15,
      "cpa": 493.58,
      "roas": 3.13
    },
    {
      "age": "35-44",
      "gender": "male",
      "impressions": 186204,
      "clicks": 2581,
      "spend": 13073.29,
      "purchases": 23,
      "purchase_value": 30091.85,
      "ctr": 1.39,
      "cpa": 568.4,
      "roas": 2.3
    },
    {
      "age": "45-54",
      "gender": "female",
      "impressions": 63906,
      "clicks": 1674,
      "spend": 7287.71,
      "purchases": 12,
      "purchase_value": 15518.05,
      "ctr": 2.62,
      "cpa": 607.31,
      "roas": 2.13
    },
    {
      "age": "65+",
      "gender": "male",
      "impressions": 37537,
      "clicks": 1044,
      "spend": 5838.58,
      "purchases": 14,
      "purchase_value": 14872.2,
      "ctr": 2.78,
      "cpa": 417.04,
      "roas": 2.55
    },
    {
      "age": "55-64",
      "gender": "female",
      "impressions": 39141,
      "clicks": 1458,
      "spend": 5837.55,
      "purchases": 8,
      "purchase_value": 9757.75,
      "ctr": 3.72,
      "cpa": 729.69,
      "roas": 1.67
    },
    {
      "age": "35-44",
      "gender": "female",
      "impressions": 62663,
      "clicks": 1105,
      "spend": 5557.69,
      "purchases": 5,
      "purchase_value": 5200.45,
      "ctr": 1.76,
      "cpa": 1111.54,
      "roas": 0.94
    },
    {
      "age": "25-34",
      "gender": "male",
      "impressions": 57834,
      "clicks": 817,
      "spend": 3169.8,
      "purchases": 6,
      "purchase_value": 6299.6,
      "ctr": 1.41,
      "cpa": 528.3,
      "roas": 1.99
    },
    {
      "age": "65+",
      "gender": "female",
      "impressions": 12036,
      "clicks": 597,
      "spend": 2083.24,
      "purchases": 5,
      "purchase_value": 5335.3,
      "ctr": 4.96,
      "cpa": 416.65,
      "roas": 2.56
    },
    {
      "age": "25-34",
      "gender": "female",
      "impressions": 31888,
      "clicks": 444,
      "spend": 1504.37,
      "purchases": 5,
      "purchase_value": 4825.3,
      "ctr": 1.39,
      "cpa": 300.87,
      "roas": 3.21
    },
    {
      "age": "45-54",
      "gender": "unknown",
      "impressions": 3866,
      "clicks": 94,
      "spend": 357.91,
      "purchases": 3,
      "purchase_value": 2599.3,
      "ctr": 2.43,
      "cpa": 119.3,
      "roas": 7.26
    },
    {
      "age": "18-24",
      "gender": "male",
      "impressions": 6731,
      "clicks": 109,
      "spend": 290.13,
      "purchases": 0,
      "purchase_value": 0.0,
      "ctr": 1.62,
      "cpa": 0,
      "roas": 0.0
    },
    {
      "age": "18-24",
      "gender": "female",
      "impressions": 7812,
      "clicks": 94,
      "spend": 244.49,
      "purchases": 0,
      "purchase_value": 0.0,
      "ctr": 1.2,
      "cpa": 0,
      "roas": 0.0
    },
    {
      "age": "55-64",
      "gender": "unknown",
      "impressions": 1374,
      "clicks": 51,
      "spend": 226.11,
      "purchases": 0,
      "purchase_value": 0.0,
      "ctr": 3.71,
      "cpa": 0,
      "roas": 0.0
    },
    {
      "age": "65+",
      "gender": "unknown",
      "impressions": 519,
      "clicks": 23,
      "spend": 223.03,
      "purchases": 0,
      "purchase_value": 0.0,
      "ctr": 4.43,
      "cpa": 0,
      "roas": 0.0
    },
    {
      "age": "35-44",
      "gender": "unknown",
      "impressions": 2212,
      "clicks": 33,
      "spend": 168.56,
      "purchases": 2,
      "purchase_value": 1528.3,
      "ctr": 1.49,
      "cpa": 84.28,
      "roas": 9.07
    },
    {
      "age": "25-34",
      "gender": "unknown",
      "impressions": 916,
      "clicks": 14,
      "spend": 80.8,
      "purchases": 0,
      "purchase_value": 0.0,
      "ctr": 1.53,
      "cpa": 0,
      "roas": 0.0
    },
    {
      "age": "18-24",
      "gender": "unknown",
      "impressions": 277,
      "clicks": 4,
      "spend": 16.03,
      "purchases": 0,
      "purchase_value": 0.0,
      "ctr": 1.44,
      "cpa": 0,
      "roas": 0.0
    },
    {
      "age": "Unknown",
      "gender": "unknown",
      "impressions": 1,
      "clicks": 0,
      "spend": 0.01,
      "purchases": 0,
      "purchase_value": 0.0,
      "ctr": 0.0,
      "cpa": 0,
      "roas": 0.0
    }
  ],
  "totals": {
    "impressions": 844569,
    "clicks": 16520,
    "spend": 82468.82,
    "purchases": 152,
    "purchase_value": 188980.6,
    "roas": 2.29
  }
}