{
  "metadata": {
    "account_id": "3372190019772184",
    "account_name": "Regula",
    "period": "3d",
    "date_range": "2025-09-11..2025-09-13",
    "generated_at": "2025-09-14T23:04:30.633876Z",
    "source": "insights(level=adset, breakdowns=[age,gender])"
  },
  "segments": [
    {
      "age": "35-44",
      "gender": "female",
      "impressions": 244297,
      "clicks": 3643,
      "spend": 16757.32,
      "purchases": 22,
      "purchase_value": 35559.17,
      "ctr": 1.49,
      "cpa": 761.7,
      "roas": 2.12
    },
    {
      "age": "25-34",
      "gender": "female",
      "impressions": 158584,
      "clicks": 1873,
      "spend": 7842.45,
      "purchases": 17,
      "purchase_value": 28714.1,
      "ctr": 1.18,
      "cpa": 461.32,
      "roas": 3.66
    },
    {
      "age": "45-54",
      "gender": "female",
      "impressions": 81588,
      "clicks": 1778,
      "spend": 7530.67,
      "purchases": 13,
      "purchase_value": 17727.97,
      "ctr": 2.18,
      "cpa": 579.28,
      "roas": 2.35
    },
    {
      "age": "18-24",
      "gender": "female",
      "impressions": 27377,
      "clicks": 375,
      "spend": 847.64,
      "purchases": 0,
      "purchase_value": 0.0,
      "ctr": 1.37,
      "cpa": 0,
      "roas": 0.0
    },
    {
      "age": "55-64",
      "gender": "female",
      "impressions": 6298,
      "clicks": 298,
      "spend": 723.81,
      "purchases": 1,
      "purchase_value": 4404.0,
      "ctr": 4.73,
      "cpa": 723.81,
      "roas": 6.08
    },
    {
      "age": "65+",
      "gender": "female",
      "impressions": 4392,
      "clicks": 167,
      "spend": 346.51,
      "purchases": 0,
      "purchase_value": 0.0,
      "ctr": 3.8,
      "cpa": 0,
      "roas": 0.0
    },
    {
      "age": "35-44",
      "gender": "unknown",
      "impressions": 4075,
      "clicks": 68,
      "spend": 292.13,
      "purchases": 1,
      "purchase_value": 1462.0,
      "ctr": 1.67,
      "cpa": 292.13,
      "roas": 5.0
    },
    {
      "age": "35-44",
      "gender": "male",
      "impressions": 4418,
      "clicks": 70,
      "spend": 198.82,
      "purchases": 1,
      "purchase_value": 694.0,
      "ctr": 1.58,
      "cpa": 198.82,
      "roas": 3.49
    },
    {
      "age": "45-54",
      "gender": "unknown",
      "impressions": 1616,
      "clicks": 29,
      "spend": 167.13,
      "purchases": 0,
      "purchase_value": 0.0,
      "ctr": 1.79,
      "cpa": 0,
      "roas": 0.0
    },
    {
      "age": "45-54",
      "gender": "male",
      "impressions": 2167,
      "clicks": 59,
      "spend": 114.13,
      "purchases": 0,
      "purchase_value": 0.0,
      "ctr": 2.72,
      "cpa": 0,
      "roas": 0.0
    },
    {
      "age": "25-34",
      "gender": "male",
      "impressions": 1950,
      "clicks": 38,
      "spend": 92.79,
      "purchases": 0,
      "purchase_value": 0.0,
      "ctr": 1.95,
      "cpa": 0,
      "roas": 0.0
    },
    {
      "age": "25-34",
      "gender": "unknown",
      "impressions": 1852,
      "clicks": 21,
      "spend": 82.63,
      "purchases": 0,
      "purchase_value": 0.0,
      "ctr": 1.13,
      "cpa": 0,
      "roas": 0.0
    },
    {
      "age": "18-24",
      "gender": "male",
      "impressions": 456,
      "clicks": 15,
      "spend": 26.77,
      "purchases": 0,
      "purchase_value": 0.0,
      "ctr": 3.29,
      "cpa": 0,
      "roas": 0.0
    },
    {
      "age": "55-64",
      "gender": "unknown",
      "impressions": 111,
      "clicks": 7,
      "spend": 22.11,
      "purchases": 0,
      "purchase_value": 0.0,
      "ctr": 6.31,
      "cpa": 0,
      "roas": 0.0
    },
    {
      "age": "18-24",
      "gender": "unknown",
      "impressions": 611,
      "clicks": 10,
      "spend": 19.28,
      "purchases": 0,
      "purchase_value": 0.0,
      "ctr": 1.64,
      "cpa": 0,
      "roas": 0.0
    },
    {
      "age": "55-64",
      "gender": "male",
      "impressions": 389,
      "clicks": 20,
      "spend": 19.23,
      "purchases": 0,
      "purchase_value": 0.0,
      "ctr": 5.14,
      "cpa": 0,
      "roas": 0.0
    },
    {
      "age": "65+",
      "gender": "male",
      "impressions": 225,
      "clicks": 17,
      "spend": 8.79,
      "purchases": 0,
      "purchase_value": 0.0,
      "ctr": 7.56,
      "cpa": 0,
      "roas": 0.0
    },
    {
      "age": "65+",
      "gender": "unknown",
      "impressions": 143,
      "clicks": 2,
      "spend": 8.03,
      "purchases": 0,
      "purchase_value": 0.0,
      "ctr": 1.4,
      "cpa": 0,
      "roas": 0.0
    },
    {
      "age": "Unknown",
      "gender": "unknown",
      "impressions": 0,
      "clicks": 0,
      "spend": 0.0,
      "purchases": 0,
      "purchase_value": 0.0,
      "ctr": 0,
      "cpa": 0,
      "roas": 0
    }
  ],
  "totals": {
    "impressions": 540549,
    "clicks": 8490,
    "spend": 35100.24,
    "purchases": 55,
    "purchase_value": 88561.24,
    "roas": 2.52
  }
}